ecoport/__init__.py
ecoport/__main__.py
ecoport-0.0.1.dist-info/LICENSE
ecoport-0.0.1.dist-info/METADATA
ecoport-0.0.1.dist-info/WHEEL
ecoport-0.0.1.dist-info/entry_points.txt
ecoport-0.0.1.dist-info/top_level.txt
ecoport-0.0.1.dist-info/RECORD
