Metadata-Version: 2.1
Name: ecoport
Version: 0.0.1
Summary: Eiphy's Conda Export
Author-email: Bai Huanyu <eiphnix@gmail.com>
License: MIT License        
Project-URL: repository, https://github.com/eiphy/conda-export
Keywords: package management
Classifier: License :: OSI Approved :: MIT License
Classifier: Programming Language :: Python
Classifier: Programming Language :: Python :: 3
Requires-Python: >=3.7
License-File: LICENSE
Requires-Dist: pyyaml
